{
  "MainPic_dishes_1": "img/MainPic_dishes_1.jpg",
  "MainPic_dishes_2": "img/MainPic_dishes_2.jpg",
  "MainPic_dishes_3": "img/MainPic_dishes_3.jpg",
  "MainPic_dishes_4":"img/MainPic_dishes_4.jpg",
  "MainPic_dishes_5": "img/MainPic_dishes_5.jpg",
  "MainPic_dishes_6": "img/MainPic_dishes_6.jpg",
  "Gallery_pic_1": "img/Gallery_pic_1.png",
  "Gallery_pic_2": "img/Gallery_pic_2.png",
  "Gallery_pic_3": "img/Gallery_pic_3.png",
  "Gallery_pic_4": "img/Gallery_pic_4.png",
  "Gallery_pic_5": "img/Gallery_pic_5.png"
}